wsshuttle/__init__.py
wsshuttle/__main__.py
wsshuttle/cmdline.py
wsshuttle/listener.py
wsshuttle/utils.py
wsshuttle-0.0.1.dist-info/LICENSE
wsshuttle-0.0.1.dist-info/METADATA
wsshuttle-0.0.1.dist-info/WHEEL
wsshuttle-0.0.1.dist-info/top_level.txt
wsshuttle-0.0.1.dist-info/RECORD
