Metadata-Version: 2.1
Name: wsshuttle
Version: 0.0.1
Summary: A tool to tunnel TCP via WinRM
Home-page: https://github.com/clubby789/wsshuttle
Author: Jamie Hill-Daniel
Author-email: clubby789@gmail.com
License: UNKNOWN
Project-URL: Bug Tracker, https://github.com/clubby789/wsshuttle/issues
Platform: UNKNOWN
Classifier: Programming Language :: Python :: 3
Classifier: License :: OSI Approved :: MIT License
Classifier: Operating System :: OS Independent
Requires-Python: >=3.5
License-File: LICENSE
Requires-Dist: pywinrm (==0.4.2)
Requires-Dist: requests-ntlm
